odoo9_addon_medical_base_us-9.0.1.0.0.99.dev6-py2.7-nspkg.pth
odoo9_addon_medical_base_us-9.0.1.0.0.99.dev6.dist-info/DESCRIPTION.rst
odoo9_addon_medical_base_us-9.0.1.0.0.99.dev6.dist-info/METADATA
odoo9_addon_medical_base_us-9.0.1.0.0.99.dev6.dist-info/RECORD
odoo9_addon_medical_base_us-9.0.1.0.0.99.dev6.dist-info/WHEEL
odoo9_addon_medical_base_us-9.0.1.0.0.99.dev6.dist-info/metadata.json
odoo9_addon_medical_base_us-9.0.1.0.0.99.dev6.dist-info/namespace_packages.txt
odoo9_addon_medical_base_us-9.0.1.0.0.99.dev6.dist-info/top_level.txt
odoo_addons/medical_base_us/README.rst
odoo_addons/medical_base_us/__init__.py
odoo_addons/medical_base_us/__openerp__.py
odoo_addons/medical_base_us/i18n/es_CO.po
odoo_addons/medical_base_us/i18n/pt_BR.po
odoo_addons/medical_base_us/models/__init__.py
odoo_addons/medical_base_us/models/medical_abstract_dea.py
odoo_addons/medical_base_us/models/medical_abstract_luhn.py
odoo_addons/medical_base_us/models/medical_abstract_npi.py
odoo_addons/medical_base_us/static/description/icon.png
odoo_addons/medical_base_us/tests/__init__.py
odoo_addons/medical_base_us/tests/test_medical_dea_abstract.py
odoo_addons/medical_base_us/tests/test_medical_luhn_abstract.py
odoo_addons/medical_base_us/tests/test_medical_npi_abstract.py
